tidal_algorithmic_mixes/__init__.py
tidal_algorithmic_mixes/discovery_mix/__init__.py
tidal_algorithmic_mixes/discovery_mix/daily_update_transformation.py
tidal_algorithmic_mixes/discovery_mix/observed_tracks_aggregator_transformation.py
tidal_algorithmic_mixes/discovery_mix/post_processor_transformation.py
tidal_algorithmic_mixes/discovery_mix/sasrec_model_transformation.py
tidal_algorithmic_mixes/etl_model.py
tidal_algorithmic_mixes/utils/__init__.py
tidal_algorithmic_mixes/utils/config.py
tidal_algorithmic_mixes/utils/constants.py
tidal_algorithmic_mixes/utils/mix_utils.py
tidal_algorithmic_mixes/utils/transformers/__init__.py
tidal_algorithmic_mixes/utils/transformers/artist/__init__.py
tidal_algorithmic_mixes/utils/transformers/artist/artist_index_enricher_transformer.py
tidal_algorithmic_mixes/utils/transformers/artist/artist_top_tracks_mix_output_transformer.py
tidal_algorithmic_mixes/utils/transformers/artist/enrich_with_artist_cluster.py
tidal_algorithmic_mixes/utils/transformers/artist/enrich_with_similar_artist.py
tidal_algorithmic_mixes/utils/transformers/artist/main_artist_compound_mapping_transformer.py
tidal_algorithmic_mixes/utils/transformers/blacklist/__init__.py
tidal_algorithmic_mixes/utils/transformers/blacklist/user_blacklist_filter_transformer.py
tidal_algorithmic_mixes/utils/transformers/discovery_mix/__init__.py
tidal_algorithmic_mixes/utils/transformers/discovery_mix/discovery_mix_output_transformer.py
tidal_algorithmic_mixes/utils/transformers/discovery_mix/discovery_mix_sort_transformer.py
tidal_algorithmic_mixes/utils/transformers/discovery_mix/flag_known_artists_transformer.py
tidal_algorithmic_mixes/utils/transformers/discovery_mix/split_by_known_artists_transformer.py
tidal_algorithmic_mixes/utils/transformers/diversity_sort_transformer.py
tidal_algorithmic_mixes/utils/transformers/posexplode_transformer.py
tidal_algorithmic_mixes/utils/transformers/user/__init__.py
tidal_algorithmic_mixes-0.2.0.dist-info/METADATA
tidal_algorithmic_mixes-0.2.0.dist-info/WHEEL
tidal_algorithmic_mixes-0.2.0.dist-info/licenses/LICENSE
tidal_algorithmic_mixes-0.2.0.dist-info/RECORD
