Metadata-Version: 2.4
Name: tidal_algorithmic_mixes
Version: 0.2.0
Summary: Algorithic mixes developed by the TIDAL personalization team.
License: Apache-2.0
License-File: LICENSE
Author: Loay
Author-email: loay@squareup.com
Requires-Python: >=3.12.0
Classifier: License :: OSI Approved :: Apache Software License
Classifier: Programming Language :: Python :: 3
Classifier: Programming Language :: Python :: 3.12
Classifier: Programming Language :: Python :: 3.13
Classifier: Programming Language :: Python :: 3.14
Requires-Dist: mlflow-skinny (>=3.0.1)
Requires-Dist: numpy (>=2.1.3,<3.0.0)
Requires-Dist: pandas (>=2.3.2,<3.0.0)
Requires-Dist: pyspark (>=4.0.0)
Requires-Dist: tidal-per-transformers (>=0.5.0)
Requires-Dist: torch (==2.2.1)
Project-URL: Homepage, https://github.com/tidal-music/tidal-algorithmic-mixes
